teachable_machine_lite.py
teachable_machine_lite-1.2.0.2.dist-info/LICENSE
teachable_machine_lite-1.2.0.2.dist-info/METADATA
teachable_machine_lite-1.2.0.2.dist-info/WHEEL
teachable_machine_lite-1.2.0.2.dist-info/top_level.txt
teachable_machine_lite-1.2.0.2.dist-info/RECORD
