Metadata-Version: 2.1
Name: teachable-machine-lite
Version: 1.2.0.2
Summary: A lightweight Python package optimized for integrating exported models from Google's Teachable Machine Platform into robotics and embedded systems environments. This streamlined version of Teachable Machine Package is specifically designed for resource-constrained devices, making it easier to deploy and use your trained models in embedded applications.
Home-page: https://github.com/MeqdadDev/teachable-machine-lite/
Author: Meqdad Dev
Author-email: meqdad.darweesh@gmail.com
Classifier: Programming Language :: Python :: 3
Classifier: Programming Language :: Python :: 3.7
Classifier: Programming Language :: Python :: 3.8
Classifier: Programming Language :: Python :: 3.9
Classifier: Programming Language :: Python :: 3.10
Classifier: Programming Language :: Python :: 3.11
Classifier: Programming Language :: Python :: 3.12
Classifier: Programming Language :: Python :: 3.13
Classifier: Topic :: Scientific/Engineering :: Image Processing
Classifier: Topic :: Scientific/Engineering :: Image Recognition
Classifier: Topic :: Scientific/Engineering :: Information Analysis
Classifier: License :: OSI Approved :: MIT License
Classifier: Operating System :: OS Independent
Requires-Python: >=3.7
License-File: LICENSE
Requires-Dist: numpy==1.26.4
Requires-Dist: tflite-runtime
Requires-Dist: Pillow
